{
  "topic": "other",
  "page": 3,
  "pageSize": 48,
  "totalPages": 3,
  "totalGroups": 109,
  "groups": [
    {
      "id": "group-1767645462518",
      "name": "重音 tetoSV｜Kasane TetoSV",
      "icon": "https://cdn3.ldstatic.com/original/4X/9/c/e/9ce9259212f14b73289b6b98c082d8a76218ae83.avif",
      "topic": "other",
      "order": 263,
      "emojiCount": 20,
      "isArchived": false
    },
    {
      "id": "group-1767645514114",
      "name": "铃仙｜Reisen",
      "icon": "https://cdn3.ldstatic.com/original/4X/a/8/b/a8b92d92858b2f8020885c6d0cc68b50e481bf67.avif",
      "topic": "other",
      "order": 265,
      "emojiCount": 20,
      "isArchived": false
    },
    {
      "id": "group-1765972558970",
      "name": "铃牙茶茶",
      "icon": "https://cdn3.ldstatic.com/original/4X/7/e/0/7e04eae53d11673e12c356073dff50bb6242067d.webp",
      "topic": "other",
      "order": 267,
      "emojiCount": 81,
      "isArchived": false
    },
    {
      "id": "group-1767645575781",
      "name": "雾雨魔理沙｜Kirisame Marisa",
      "icon": "https://cdn3.ldstatic.com/original/4X/c/9/e/c9e433e439e8bbddf1978358a14aabd5d25e3ff2.avif",
      "topic": "other",
      "order": 272,
      "emojiCount": 54,
      "isArchived": false
    },
    {
      "id": "group-1761446644760",
      "name": "風間白花",
      "icon": "https://cdn3.ldstatic.com/original/4X/5/c/8/5c8016aa6233bdcdc60c984e2bbc60f8a2097dab.webp",
      "topic": "other",
      "order": 273,
      "emojiCount": 16,
      "isArchived": false
    },
    {
      "id": "group-1762523521486",
      "name": "魔女",
      "icon": "https://cdn3.ldstatic.com/original/4X/0/9/c/09cd510aa8834074c5d94d118f9f5683b8419bdf.webp",
      "topic": "other",
      "order": 274,
      "emojiCount": 92,
      "isArchived": false
    },
    {
      "id": "group-1755966299851",
      "name": "魔女的夜宴",
      "icon": "https://cdn3.ldstatic.com/original/4X/c/f/7/cf7a66e61f5d8179e67d3c73781cb61b08b85ec1.webp",
      "topic": "other",
      "order": 275,
      "emojiCount": 38,
      "isArchived": false
    },
    {
      "id": "group-1764980488364",
      "name": "魔法少女的魔女审判 by 绮纪",
      "icon": "https://cdn3.ldstatic.com/original/4X/b/5/0/b506a1d289f260374437e310870e0fa91e11dca8.jpeg",
      "topic": "other",
      "order": 277,
      "emojiCount": 14,
      "isArchived": true
    },
    {
      "id": "group-1762524245454",
      "name": "魔裁补充包",
      "icon": "https://cdn3.ldstatic.com/original/4X/9/e/9/9e95a3ed14fbdb06225a60eca85a66286e821bf3.webp",
      "topic": "other",
      "order": 278,
      "emojiCount": 45,
      "isArchived": false
    },
    {
      "id": "group-1767645584240",
      "name": "鳰原令王那｜Nyubara Reona",
      "icon": "https://cdn3.ldstatic.com/original/4X/9/0/a/90a9235602ae1647167436610b28c058c01c5b07.avif",
      "topic": "other",
      "order": 280,
      "emojiCount": 20,
      "isArchived": false
    },
    {
      "id": "group-1755913842696",
      "name": "黄",
      "icon": "https://cdn3.ldstatic.com/original/4X/c/3/8/c38f18581aafd9d9eae31b67c91261cc336072b6.webp",
      "topic": "other",
      "order": 284,
      "emojiCount": 85,
      "isArchived": false
    },
    {
      "id": "group-1767644542108",
      "name": "墨提斯｜Mortis",
      "icon": "https://cdn3.ldstatic.com/original/4X/2/d/d/2dd1788f2e5bdb0f0b15a3c2bd537af1d2f685ca.avif",
      "topic": "other",
      "order": 285,
      "emojiCount": 48,
      "isArchived": false
    },
    {
      "id": "group-1763038870366",
      "name": "🍟 藤田言音",
      "icon": "https://cdn3.ldstatic.com/original/4X/6/d/4/6d490b7ac0c7b80ac7ecae455b9f928ee151df92.avif",
      "topic": "other",
      "order": 286,
      "emojiCount": 49,
      "isArchived": false
    }
  ]
}