{
  "id": "group-1755913887877",
  "name": "neko2",
  "icon": "https://linux.do/uploads/default/original/4X/f/7/a/f7afaab5dd91159674a53cdc977a09402f66c278.webp",
  "order": 4,
  "emojis": [
    {
      "id": "emoji-1755913930434-9c0wvt",
      "packet": 1755913930434,
      "name": "挥手打招呼",
      "url": "https://linux.do/uploads/default/original/4X/7/d/7/7d79706009cad4c418d71a2ec801db1148f15def.webp",
      "width": 512,
      "height": 495,
      "groupId": "group-1755913887877"
    },
    {
      "id": "emoji-1755913930435-3sjse8",
      "packet": 1755913930435,
      "name": "我回来了",
      "url": "https://linux.do/uploads/default/original/4X/4/3/9/43922b23ca7dfef5506541d87caf616618d5f6fa.webp",
      "width": 501,
      "height": 512,
      "groupId": "group-1755913887877"
    },
    {
      "id": "emoji-1755913930435-hi6x75",
      "packet": 1755913930435,
      "name": "你还好吗",
      "url": "https://linux.do/uploads/default/original/4X/9/1/b/91bafe5b5494b203c5b656280658a68fd6d14089.webp",
      "width": 486,
      "height": 512,
      "groupId": "group-1755913887877"
    },
    {
      "id": "emoji-1755913930435-71cy0b",
      "packet": 1755913930435,
      "name": "思考中",
      "url": "https://linux.do/uploads/default/original/4X/0/e/b/0ebdeeb36be010453470b8f7c3d211c5c8bc2bb1.webp",
      "width": 428,
      "height": 512,
      "groupId": "group-1755913887877"
    },
    {
      "id": "emoji-1755913930435-qaan7v",
      "packet": 1755913930435,
      "name": "热情欢迎",
      "url": "https://linux.do/uploads/default/original/4X/b/5/d/b5d47178a28be540f091dd7a21ef1030cc92f2c7.webp",
      "width": 512,
      "height": 481,
      "groupId": "group-1755913887877"
    },
    {
      "id": "emoji-1755913930435-f74jxg",
      "packet": 1755913930435,
      "name": "耶 胜利",
      "url": "https://linux.do/uploads/default/original/4X/0/1/6/0167120ced7bfd323f27778cf9cd6caa4077ea3f.webp",
      "width": 505,
      "height": 512,
      "groupId": "group-1755913887877"
    },
    {
      "id": "emoji-1755913930435-2ndsz7",
      "packet": 1755913930435,
      "name": "咬手指沉思",
      "url": "https://linux.do/uploads/default/original/4X/0/a/e/0aef5066d257b3343f4a7dc9b65783295246a2f3.webp",
      "width": 512,
      "height": 499,
      "groupId": "group-1755913887877"
    },
    {
      "id": "emoji-1755913930435-hqhbhi",
      "packet": 1755913930435,
      "name": "哭泣要钱",
      "url": "https://linux.do/uploads/default/original/4X/5/b/e/5beb09f7ec66c083a9261427c06a1b0066e16693.webp",
      "width": 489,
      "height": 512,
      "groupId": "group-1755913887877"
    },
    {
      "id": "emoji-1755913930435-bdy4a1",
      "packet": 1755913930435,
      "name": "得意的笑",
      "url": "https://linux.do/uploads/default/original/4X/0/f/3/0f3972e2967ca49ca0a3e187d6000ff91127c1fe.webp",
      "width": 512,
      "height": 479,
      "groupId": "group-1755913887877"
    },
    {
      "id": "emoji-1755913930435-5890s3",
      "packet": 1755913930435,
      "name": "看手机",
      "url": "https://linux.do/uploads/default/original/4X/f/a/b/fab0e13bd0dd7d7bf89fe25e8f3c01117a4b092f.webp",
      "width": 441,
      "height": 512,
      "groupId": "group-1755913887877"
    },
    {
      "id": "emoji-1755913930435-y77dlc",
      "packet": 1755913930435,
      "name": "猫耳少女抱玩偶",
      "url": "https://linux.do/uploads/default/original/4X/e/e/f/eefad90bfb1f1ee3c33fb1bbf009b013a9e5ef21.webp",
      "width": 508,
      "height": 512,
      "groupId": "group-1755913887877"
    },
    {
      "id": "emoji-1755913930435-mseywy",
      "packet": 1755913930435,
      "name": "猫耳少女沮丧",
      "url": "https://linux.do/uploads/default/original/4X/5/5/7/557b1ac5ee247ae0549622bc8b5f4de30b3c47a2.webp",
      "width": 396,
      "height": 512,
      "groupId": "group-1755913887877"
    },
    {
      "id": "emoji-1755913930435-e99jam",
      "packet": 1755913930435,
      "name": "猫耳少女举着愤怒牌",
      "url": "https://linux.do/uploads/default/original/4X/7/9/5/7957dd786175a5af36bc605bc9472240629e08e7.webp",
      "width": 502,
      "height": 512,
      "groupId": "group-1755913887877"
    },
    {
      "id": "emoji-1755913930435-yif84g",
      "packet": 1755913930435,
      "name": "猫耳少女哭泣",
      "url": "https://linux.do/uploads/default/original/4X/8/4/0/840eac911e0d08532aa6636456933d0d24c5e231.webp",
      "width": 512,
      "height": 512,
      "groupId": "group-1755913887877"
    },
    {
      "id": "emoji-1755913930435-jvi5w9",
      "packet": 1755913930435,
      "name": "猫耳少女吃鲷鱼烧",
      "url": "https://linux.do/uploads/default/original/4X/f/4/7/f477db3f5ea2b407913b9a88022dbed2c5672b3e.webp",
      "width": 470,
      "height": 512,
      "groupId": "group-1755913887877"
    },
    {
      "id": "emoji-1755913930435-nbeecj",
      "packet": 1755913930435,
      "name": "猫耳少女趴着",
      "url": "https://linux.do/uploads/default/original/4X/9/1/b/91bdef896887986ca65fc3853e04571e808524ba.webp",
      "width": 512,
      "height": 381,
      "groupId": "group-1755913887877"
    },
    {
      "id": "emoji-1755913930435-m1dk8p",
      "packet": 1755913930435,
      "name": "猫耳少女站立",
      "url": "https://linux.do/uploads/default/original/4X/c/6/9/c6927a64ac6a479891e8e427140c0505ea54cc39.webp",
      "width": 326,
      "height": 512,
      "groupId": "group-1755913887877"
    },
    {
      "id": "emoji-1755913930435-xpjbtu",
      "packet": 1755913930435,
      "name": "白发少女不满",
      "url": "https://linux.do/uploads/default/original/4X/c/b/d/cbd5117b0d8c7d6b1891c91a69777e9ae55697b7.webp",
      "width": 467,
      "height": 512,
      "groupId": "group-1755913887877"
    },
    {
      "id": "emoji-1755913930435-kk9c18",
      "packet": 1755913930435,
      "name": "白发少女玩手机",
      "url": "https://linux.do/uploads/default/original/4X/9/5/3/953aa2c07ab48fc7da93e8812e83ed4ebebb8321.webp",
      "width": 464,
      "height": 512,
      "groupId": "group-1755913887877"
    },
    {
      "id": "emoji-1755913930436-owmmsc",
      "packet": 1755913930436,
      "name": "白发少女抱粉色玩偶睡着",
      "url": "https://linux.do/uploads/default/original/4X/e/2/6/e26c6d4ffb0846a0fc500b61c1fc92d073d07178.webp",
      "width": 464,
      "height": 512,
      "groupId": "group-1755913887877"
    },
    {
      "id": "emoji-1755913930436-mk6ohw",
      "packet": 1755913930436,
      "name": "无聊地玩手机",
      "url": "https://linux.do/uploads/default/original/4X/6/8/f/68f8c22b431b80da8408e77f0e9af350c2dc35a3.webp",
      "width": 454,
      "height": 512,
      "groupId": "group-1755913887877"
    },
    {
      "id": "emoji-1755913930436-eznb44",
      "packet": 1755913930436,
      "name": "开心雀跃",
      "url": "https://linux.do/uploads/default/original/4X/3/2/6/326a9dd0bd196c048a276711ba2216c586bfeabf.webp",
      "width": 489,
      "height": 512,
      "groupId": "group-1755913887877"
    },
    {
      "id": "emoji-1755913930436-zvyhqf",
      "packet": 1755913930436,
      "name": "挥手再见",
      "url": "https://linux.do/uploads/default/original/4X/3/7/8/3787a7d0e7492a949193b9de51f69aa9d606fd64.webp",
      "width": 467,
      "height": 512,
      "groupId": "group-1755913887877"
    },
    {
      "id": "emoji-1755913930436-vqw7w5",
      "packet": 1755913930436,
      "name": "探头好奇",
      "url": "https://linux.do/uploads/default/original/4X/2/7/5/27548691a52388f3a6ee43da02a4d993071e5507.webp",
      "width": 512,
      "height": 365,
      "groupId": "group-1755913887877"
    },
    {
      "id": "emoji-1755913930436-b1b1r1",
      "packet": 1755913930436,
      "name": "抱着玩偶",
      "url": "https://linux.do/uploads/default/original/4X/5/e/8/5e8ee3aaba7473f1bb580a5268d20534c52026ff.webp",
      "width": 467,
      "height": 512,
      "groupId": "group-1755913887877"
    },
    {
      "id": "emoji-1755913930436-v4dayr",
      "packet": 1755913930436,
      "name": "献花祝贺",
      "url": "https://linux.do/uploads/default/original/4X/e/5/6/e56a2fa65e96b6eedc367b026bf5bf8efb9b4740.webp",
      "width": 466,
      "height": 512,
      "groupId": "group-1755913887877"
    },
    {
      "id": "emoji-1755913930436-ta0kc4",
      "packet": 1755913930436,
      "name": "拥抱感谢",
      "url": "https://linux.do/uploads/default/original/4X/1/0/a/10a5698a432fe7be8bfd950cbc13cd06182a5912.webp",
      "width": 499,
      "height": 512,
      "groupId": "group-1755913887877"
    },
    {
      "id": "emoji-1755913930436-kx6ann",
      "packet": 1755913930436,
      "name": "伤心哭泣",
      "url": "https://linux.do/uploads/default/original/4X/1/5/0/150be6d2d974f8b9c3c518851b497afa14620efd.webp",
      "width": 476,
      "height": 512,
      "groupId": "group-1755913887877"
    },
    {
      "id": "emoji-1755913930436-jfnva1",
      "packet": 1755913930436,
      "name": "疑惑不解",
      "url": "https://linux.do/uploads/default/original/4X/e/2/4/e24604804329256a5042178454b6bac69df51714.webp",
      "width": 470,
      "height": 512,
      "groupId": "group-1755913887877"
    },
    {
      "id": "emoji-1755913930436-9nh4dv",
      "packet": 1755913930436,
      "name": "表示理解",
      "url": "https://linux.do/uploads/default/original/4X/c/1/5/c1535fc14fc1b5054a923d4c37abc4ef89fd6632.webp",
      "width": 489,
      "height": 512,
      "groupId": "group-1755913887877"
    },
    {
      "id": "emoji-1755913930436-u4gpm0",
      "packet": 1755913930436,
      "name": "草莓蛋糕",
      "url": "https://linux.do/uploads/default/original/4X/f/7/a/f7afaab5dd91159674a53cdc977a09402f66c278.webp",
      "width": 473,
      "height": 512,
      "groupId": "group-1755913887877"
    },
    {
      "id": "emoji-1755913930436-w69xz7",
      "packet": 1755913930436,
      "name": "拥抱",
      "url": "https://linux.do/uploads/default/original/4X/6/b/9/6b93dc4e317b3d74a205b38c4041a09090c96063.webp",
      "width": 492,
      "height": 512,
      "groupId": "group-1755913887877"
    },
    {
      "id": "emoji-1755913930436-jmtsqg",
      "packet": 1755913930436,
      "name": "抱歉哭泣",
      "url": "https://linux.do/uploads/default/original/4X/8/9/9/899067d06c1dbc537e27fe5a9c6f3b61beffcbf5.webp",
      "width": 486,
      "height": 512,
      "groupId": "group-1755913887877"
    },
    {
      "id": "emoji-1755913930436-ww0s81",
      "packet": 1755913930436,
      "name": "困惑",
      "url": "https://linux.do/uploads/default/original/4X/4/3/4/43498ed609ddc3d03aeb63863a58f5906b6392b3.webp",
      "width": 512,
      "height": 490,
      "groupId": "group-1755913887877"
    },
    {
      "id": "emoji-1755913930436-kxye9q",
      "packet": 1755913930436,
      "name": "抱着小猫玩偶",
      "url": "https://linux.do/uploads/default/original/4X/b/d/a/bda18e464d66c690808ea6e541ab5c4722a84cac.webp",
      "width": 512,
      "height": 499,
      "groupId": "group-1755913887877"
    },
    {
      "id": "emoji-1755913930436-vpntpz",
      "packet": 1755913930436,
      "name": "难过道歉",
      "url": "https://linux.do/uploads/default/original/4X/8/9/9/899067d06c1dbc537e27fe5a9c6f3b61beffcbf5.webp",
      "width": 486,
      "height": 512,
      "groupId": "group-1755913887877"
    },
    {
      "id": "emoji-1755913930436-v3q5gt",
      "packet": 1755913930436,
      "name": "生气打枕头",
      "url": "https://linux.do/uploads/default/original/4X/5/0/e/50e4fca45b2018040f52e4bc892de33312fa804c.webp",
      "width": 464,
      "height": 512,
      "groupId": "group-1755913887877"
    },
    {
      "id": "emoji-1755913930436-h7iw15",
      "packet": 1755913930436,
      "name": "不要",
      "url": "https://linux.do/uploads/default/original/4X/6/e/e/6ee3b11a8cc1c2c942091fc01feb8442edc024a9.webp",
      "width": 505,
      "height": 512,
      "groupId": "group-1755913887877"
    },
    {
      "id": "emoji-1755913930436-sxwdnn",
      "packet": 1755913930436,
      "name": "早安打哈欠",
      "url": "https://linux.do/uploads/default/original/4X/3/4/b/34bee68acf12b7b5314cc069b65ab8dcc204815f.webp",
      "width": 470,
      "height": 512,
      "groupId": "group-1755913887877"
    },
    {
      "id": "emoji-1755913930436-awqnh3",
      "packet": 1755913930436,
      "name": "晚安睡觉",
      "url": "https://linux.do/uploads/default/original/4X/1/d/1/1d133d3278b18b5c09c1ac5d5ae3cd8e7d35d241.webp",
      "width": 512,
      "height": 442,
      "groupId": "group-1755913887877"
    }
  ]
}
